easypysmb/__init__.py
easypysmb/easypysmb.py
easypysmb-1.4.4.dist-info/LICENSE
easypysmb-1.4.4.dist-info/METADATA
easypysmb-1.4.4.dist-info/WHEEL
easypysmb-1.4.4.dist-info/top_level.txt
easypysmb-1.4.4.dist-info/RECORD
