Metadata-Version: 2.1
Name: easypysmb
Version: 1.4.4
Summary: Easy to use PySMB wrapper library
Home-page: https://github.com/pschmitt/easypysmb
Author: Philipp Schmitt
Author-email: philipp@schmitt.co
License: GPL3
Platform: UNKNOWN
Requires-Dist: pysmb
